MANIFEST.in
README.md
setup.cfg
setup.py
msmadapter/__init__.py
msmadapter/adaptive.py
msmadapter/model_utils.py
msmadapter/pbs_utils.py
msmadapter/plot_utils.py
msmadapter/utils.py
msmadapter.egg-info/PKG-INFO
msmadapter.egg-info/SOURCES.txt
msmadapter.egg-info/dependency_links.txt
msmadapter.egg-info/top_level.txt
msmadapter/templates/02_Heat.in
msmadapter/templates/03_Heat2.in
msmadapter/templates/Production_cmds.in
msmadapter/templates/min1.in
msmadapter/templates/min2.in
msmadapter/templates/min3.in
msmadapter/templates/template.cpptraj
msmadapter/templates/template.tleap
msmadapter/tests/.coverage
msmadapter/tests/__init__.py
msmadapter/tests/test_adaptive.py
msmadapter/tests/test_model_utils.py
msmadapter/tests/test_plot_utils.py
msmadapter/tests/test_utils.py