Metadata-Version: 1.1
Name: msmadapter
Version: 0.1rc0
Summary: Automate adaptive sampling with AMBER and MSMs
Home-page: https://github.com/jeiros/msmadapter
Author: Juan Eiros
Author-email: jeiroz@gmail.com
License: MIT
Download-URL: https://github.com/jeiros/msmadapter/archive/0.1rc.tar.gz
Platform: UNKNOWN
